mypy_gh_action_report/__init__.py
mypy_gh_action_report/converters/__init__.py
mypy_gh_action_report/converters/gha.py
mypy_gh_action_report/converters/json.py
mypy_gh_action_report/executors.py
mypy_gh_action_report/main.py
mypy_gh_action_report/models.py
mypy_gh_action_report/parser.py
mypy_gh_action_report-0.2.4.dist-info/METADATA
mypy_gh_action_report-0.2.4.dist-info/WHEEL
mypy_gh_action_report-0.2.4.dist-info/entry_points.txt
mypy_gh_action_report-0.2.4.dist-info/licenses/LICENSE
mypy_gh_action_report-0.2.4.dist-info/RECORD
