Metadata-Version: 2.4
Name: mypy-gh-action-report
Version: 0.2.4
Summary: Notify Mypy output via GitHub Workflow Commands
License: MIT
License-File: LICENSE
Author: Błażej Cyrzon
Author-email: blazej.cyrzon@gmail.com
Requires-Python: >=3.10,<4.0
Classifier: Intended Audience :: Developers
Classifier: License :: OSI Approved :: MIT License
Classifier: Programming Language :: Python
Classifier: Programming Language :: Python :: 3
Classifier: Programming Language :: Python :: 3.10
Classifier: Programming Language :: Python :: 3.11
Classifier: Programming Language :: Python :: 3.12
Classifier: Programming Language :: Python :: 3.13
Classifier: Programming Language :: Python :: 3.14
Classifier: Programming Language :: Python :: 3 :: Only
Classifier: Topic :: Software Development
Classifier: Topic :: Utilities
Requires-Dist: github-action-utils (>=1.1.0,<2.0.0)
Requires-Dist: typer (>=0.19.2,<0.20.0)
